Metadata-Version: 1.0
Name: hassan-fivehead-hahaha
Version: 1.3
Summary: Gaussian and something distributions
Home-page: UNKNOWN
Author: UNKNOWN
Author-email: UNKNOWN
License: UNKNOWN
Platform: UNKNOWN
